toolbox/__init__.py
toolbox/asyncio/__init__.py
toolbox/asyncio/cache.py
toolbox/asyncio/pattern.py
toolbox/asyncio/streams.py
toolbox/asyncio/threads.py
toolbox/builtins/__init__.py
toolbox/builtins/property.py
toolbox/collections/__init__.py
toolbox/collections/item.py
toolbox/collections/mapping.py
toolbox/collections/namedtuple.py
toolbox/config/__init__.py
toolbox/config/globalconfig.py
toolbox/functools/__init__.py
toolbox/functools/timeout.py
toolbox/pdb/__init__.py
toolbox/pdb/sprinkle.py
toolbox/pkgutil/__init__.py
toolbox/pkgutil/package.py
toolbox/sockets/__init__.py
toolbox/sockets/ip.py
toolbox/string/__init__.py
toolbox/string/color.py
toolbox/textwrap/__init__.py
toolbox/textwrap/text.py
toolbox-1.10.0.dist-info/AUTHORS
toolbox-1.10.0.dist-info/LICENSE
toolbox-1.10.0.dist-info/METADATA
toolbox-1.10.0.dist-info/WHEEL
toolbox-1.10.0.dist-info/pbr.json
toolbox-1.10.0.dist-info/top_level.txt
toolbox-1.10.0.dist-info/RECORD
