Metadata-Version: 2.1
Name: toolbox
Version: 1.10.0
Summary: Extends Python with useful features.
Home-page: https://github.com/synchronizing/toolbox
Author: Felipe Faria
Author-email: felipefaria@hey.com
License: MIT
Project-URL: Bug Tracker, https://github.com/synchronizing/toolbox/issues
Project-URL: Documentation, https://synchronizing.github.io/toolbox/
Project-URL: Source Code, https://github.com/synchronizing/toolbox/tree/master
Keywords: toolbox,asyncio,builtins,collections,config,functools,textwrap
Classifier: Programming Language :: Python :: Implementation :: CPython
Classifier: Development Status :: 5 - Production/Stable
Classifier: License :: OSI Approved :: MIT License
Classifier: Natural Language :: English
Classifier: Topic :: Software Development :: Libraries
Classifier: Topic :: Utilities
Requires-Python: >=3.7
License-File: LICENSE
License-File: AUTHORS
